{
  "name": "1714938697032sur6.jpg",
  "bucket": "storageBucket",
  "metageneration": 1,
  "generation": 1714938697046,
  "contentType": "image/jpeg",
  "storageClass": "STANDARD",
  "contentDisposition": "inline",
  "downloadTokens": [
    "59594f21-0568-46a0-9c68-8d15c1ae530a"
  ],
  "etag": "Toi2Kx7T14dVdrbYjjiyaZ4Ioo4",
  "customMetadata": {},
  "timeCreated": "2024-05-05T19:51:37.046Z",
  "updated": "2024-05-05T19:51:37.046Z",
  "size": 393200,
  "md5Hash": "nMM/OujQRaF2S3iX5nfPgg==",
  "crc32c": "789748069"
}